MANIFEST.in
setup.py
weave/__init__.py
weave/minimal/__init__.py
weave/minimal/compat.py
weave/minimal/constants.py
weave/minimal/misc.py
weave/minimal/storage.py
weave/minimal/user.py
weave/minimal/utils.py
weave/static/scratch.png
weave_minimal.egg-info/PKG-INFO
weave_minimal.egg-info/SOURCES.txt
weave_minimal.egg-info/dependency_links.txt
weave_minimal.egg-info/entry_points.txt
weave_minimal.egg-info/requires.txt
weave_minimal.egg-info/top_level.txt
weave_minimal.egg-info/zip-safe