Metadata-Version: 1.1
Name: weave-minimal
Version: 1.4.1
Summary: lightweight firefox weave/sync server
Home-page: https://github.com/posativ/weave-minimal/
Author: Martin Zimmermann
Author-email: info@posativ.org
License: BSD revised
Platform: UNKNOWN
Classifier: Development Status :: 5 - Production/Stable
Classifier: Topic :: Internet
Classifier: Topic :: Internet :: WWW/HTTP :: HTTP Servers
Classifier: Topic :: Internet :: WWW/HTTP :: WSGI :: Application
Classifier: License :: OSI Approved :: BSD License
Classifier: Programming Language :: Python :: 2.6
Classifier: Programming Language :: Python :: 2.7
Classifier: Programming Language :: Python :: 3.3
